{
  "i7yETyaGX3nftE9a": {
    "key": "nDEa7/cQuQuqJNg+7NpcH/TQOS8NgNUpZIQMYj4dHGc=",
    "iv": "s2nNr8eLboUrbJZET9Fc1A==",
    "created": "2025-08-03T14:25:41.213250",
    "expires": "2025-09-04T14:25:41.213250",
    "status": "active"
  },
  "nC0qYb8iFinYaPow": {
    "key": "nDEa7/cQuQuqJNg+7NpcH/TQOS8NgNUpZIQMYj4dHGc=",
    "iv": "s2nNr8eLboUrbJZET9Fc1A==",
    "created": "2025-08-03T14:25:41.213250",
    "expires": "2025-09-04T14:25:41.213250",
    "status": "active"
  },
  "KbnO49w3Hi9OHSDv": {
    "key": "nDEa7/cQuQuqJNg+7NpcH/TQOS8NgNUpZIQMYj4dHGc=",
    "iv": "s2nNr8eLboUrbJZET9Fc1A==",
    "created": "2025-08-03T14:25:41.213250",
    "expires": "2025-09-04T14:25:41.213250",
    "status": "active"
  },
  "A974TyGQJSFTaq06": {
    "key": "CCKshS+AcjZTGwk5QwvNfZSgMab0frD6CU5z5q1UOCU=",
    "iv": "0dUf3ESMLRWN3n9x7cDlhw==",
    "created": "2025-10-03T22:39:03.546391",
    "expires": "2025-11-04T22:39:03.546590",
    "status": "active"
  }
}
